{
  "publicPath": "/",
  "all": [
    "0.bundle.js",
    "client.bundle.js"
  ],
  "initial": [
    "client.bundle.js"
  ],
  "async": [
    "0.bundle.js"
  ],
  "modules": {
    "cf21109e": [
      1
    ],
    "8974a0ce": [
      1
    ],
    "b22a9d72": [
      1
    ],
    "6efff0ec": [
      1
    ],
    "ab947124": [
      1
    ],
    "60b68a04": [
      1
    ],
    "609a5b02": [
      1
    ],
    "607e2c00": [
      1
    ],
    "0b2040b0": [
      1
    ],
    "7924d710": [
      1
    ],
    "539c08bc": [
      1
    ],
    "22ea38d6": [
      1
    ],
    "7c21aefa": [
      1
    ],
    "0547a270": [
      1
    ],
    "592fe760": [
      1
    ],
    "1e1bb539": [
      1
    ],
    "2e1a08d0": [
      1
    ],
    "5b4a4ee0": [
      1
    ],
    "07471d6e": [
      1
    ],
    "521b9876": [
      0
    ],
    "2967550a": [
      0
    ],
    "93ff786a": [
      0
    ],
    "61301df4": [
      1
    ],
    "96b91fb8": [
      1
    ],
    "6854dcc8": [
      1
    ],
    "921324da": [
      1
    ],
    "096ae22a": [
      1
    ],
    "8557df42": [
      1
    ],
    "46ff9301": [
      1
    ],
    "68f04d59": [
      0
    ],
    "0102b1f5": [
      1
    ],
    "1cce4ef4": [
      1
    ],
    "52e09b9d": [
      1
    ],
    "869454e2": [
      1
    ],
    "1899e4ca": [
      1
    ],
    "48d71109": [
      1
    ],
    "dc4ca5b0": [
      1
    ],
    "22200d70": [
      1
    ],
    "6ec3f1b2": [
      1
    ],
    "73cfbed4": [
      1
    ],
    "0cb888ad": [
      1
    ],
    "74ba99be": [
      1
    ],
    "1ac3a50a": [
      1
    ],
    "2b977fb3": [
      0
    ],
    "47f59ece": [
      1
    ],
    "c98db12e": [
      1
    ],
    "6d6ffb56": [
      1
    ],
    "08ccb9ee": [
      1
    ],
    "7764fd44": [
      1
    ],
    "9c6d3fac": [
      1
    ],
    "35f551d2": [
      1
    ],
    "1c57ba38": [
      1
    ],
    "1fd12c2f": [
      1
    ],
    "39be2f24": [
      1
    ],
    "0d3d983e": [
      1
    ],
    "21dc8817": [
      1
    ]
  }
}